gs_openapi/__init__.py
gs_openapi/config.py
gs_openapi/main.py
gs_openapi/api/__init__.py
gs_openapi/api/maps.py
gs_openapi/api/robots.py
gs_openapi/auth/__init__.py
gs_openapi/auth/token_manager.py
gs_openapi/core/__init__.py
gs_openapi/core/client.py
gs_openapi/core/endpoints.py
gs_openapi/mcp/__init__.py
gs_openapi/mcp/gausium_mcp.py
gs_openapi/utils/robot_router.py
gs_openapi/workflows/__init__.py
gs_openapi/workflows/task_engine.py
mcp_gs_robot-0.1.12.dist-info/METADATA
mcp_gs_robot-0.1.12.dist-info/WHEEL
mcp_gs_robot-0.1.12.dist-info/entry_points.txt
mcp_gs_robot-0.1.12.dist-info/RECORD
