Metadata-Version: 2.4
Name: mcp-gs-robot
Version: 0.1.12
Summary: MCP Server for Gausium Robot OpenAPI - Control and monitor Gausium cleaning robots through AI assistants
Project-URL: Homepage, https://github.com/cfrs2005/mcp-gs-robot
Project-URL: Repository, https://github.com/cfrs2005/mcp-gs-robot
Project-URL: Issues, https://github.com/cfrs2005/mcp-gs-robot/issues
Author-email: toy <cfrs2005@gmail.com>
License: MIT
Keywords: gausium,mcp,openapi,robot
Classifier: Development Status :: 3 - Alpha
Classifier: Intended Audience :: Developers
Classifier: License :: OSI Approved :: MIT License
Classifier: Programming Language :: Python :: 3.12
Classifier: Topic :: Software Development :: Libraries :: Python Modules
Requires-Python: >=3.12
Requires-Dist: httpx>=0.28.1
Requires-Dist: mcp[cli]>=1.6.0
Requires-Dist: python-dotenv>=1.0.0
